geojsonchemy/__init__.py
geojsonchemy/py.typed
geojsonchemy-0.1.3.dist-info/LICENSE
geojsonchemy-0.1.3.dist-info/METADATA
geojsonchemy-0.1.3.dist-info/WHEEL
geojsonchemy-0.1.3.dist-info/RECORD
