Metadata-Version: 2.1
Name: geojsonchemy
Version: 0.1.3
Summary: 
Author: Nutchanon Ninyawee
Author-email: nutchanon@codustry.com
Requires-Python: >=3.11,<4.0
Classifier: Programming Language :: Python :: 3
Classifier: Programming Language :: Python :: 3.11
Classifier: Programming Language :: Python :: 3.12
Requires-Dist: geoalchemy2 (>=0.14.3,<0.15.0)
Requires-Dist: geojson-pydantic (>=1.0.2,<2.0.0)
Requires-Dist: orjson (>=3.9.13,<4.0.0)
